{"odd":{"success":1,"results":[{"FI":"75227511","event_id":"613914","asian_lines":{"updated_at":"1532570376","sp":{"asian_handicap":[{"opp":"-0.5","odds":"2.025","header":"Home"},{"opp":"+0.5","odds":"1.825","header":"Away"}],"goal_line":[{"goals":"2.0, 2.5","odds":"1.900","header":"Over"},{"goals":"2.0, 2.5","odds":"1.950","header":"Under"}],"alternative_asian_handicap":[{"opp":"-1.5, -2.0","odds":"4.800","header":"Home"},{"opp":"+1.5, +2.0","odds":"1.175","header":"Away"},{"opp":"-1.5","odds":"3.700","header":"Home"},{"opp":"+1.5","odds":"1.260","header":"Away"},{"opp":"-1.0, -1.5","odds":"3.450","header":"Home"},{"opp":"+1.0, +1.5","odds":"1.300","header":"Away"},{"opp":"-1.0","odds":"3.000","header":"Home"},{"opp":"+1.0","odds":"1.375","header":"Away"},{"opp":"-0.5, -1.0","odds":"2.300","header":"Home"},{"opp":"+0.5, +1.0","odds":"1.600","header":"Away"},{"opp":"0.0, -0.5","odds":"1.725","header":"Home"},{"opp":"0.0, +0.5","odds":"2.075","header":"Away"},{"opp":"0.0","odds":"1.475","header":"Home"},{"opp":"0.0","odds":"2.600","header":"Away"},{"opp":"0.0, +0.5","odds":"1.375","header":"Home"},{"opp":"0.0, -0.5","odds":"3.000","header":"Away"},{"opp":"+0.5","odds":"1.300","header":"Home"},{"opp":"-0.5","odds":"3.450","header":"Away"},{"opp":"+0.5, +1.0","odds":"1.190","header":"Home"},{"opp":"-0.5, -1.0","odds":"4.500","header":"Away"}],"alternative_goal_line":[{"goals":"1.0","odds":"1.100","header":"Over"},{"goals":"1.0","odds":"7.000","header":"Under"},{"goals":"1.0, 1.5","odds":"1.230","header":"Over"},{"goals":"1.0, 1.5","odds":"4.000","header":"Under"},{"goals":"1.5","odds":"1.375","header":"Over"},{"goals":"1.5","odds":"3.000","header":"Under"},{"goals":"1.5, 2.0","odds":"1.450","header":"Over"},{"goals":"1.5, 2.0","odds":"2.675","header":"Under"},{"goals":"2.0","odds":"1.600","header":"Over"},{"goals":"2.0","odds":"2.300","header":"Under"},{"goals":"2.5","odds":"2.100","header":"Over"},{"goals":"2.5","odds":"1.700","header":"Under"},{"goals":"2.5, 3.0","odds":"2.425","header":"Over"},{"goals":"2.5, 3.0","odds":"1.525","header":"Under"},{"goals":"3.0","odds":"3.100","header":"Over"},{"goals":"3.0","odds":"1.350","header":"Under"},{"goals":"3.0, 3.5","odds":"3.450","header":"Over"},{"goals":"3.0, 3.5","odds":"1.300","header":"Under"},{"goals":"3.5","odds":"3.800","header":"Over"},{"goals":"3.5","odds":"1.250","header":"Under"},{"goals":"3.5, 4.0","odds":"4.800","header":"Over"},{"goals":"3.5, 4.0","odds":"1.175","header":"Under"},{"goals":"4.0","odds":"7.000","header":"Over"},{"goals":"4.0","odds":"1.100","header":"Under"}],"1st_half_asian_handicap":[{"opp":"0.0, -0.5","odds":"2.100","header":"Home"},{"opp":"0.0, +0.5","odds":"1.700","header":"Away"}],"1st_half_goal_line":[{"goals":"1.0","odds":"2.075","header":"Over"},{"goals":"1.0","odds":"1.725","header":"Under"}],"alternative_1st_half_asian_handicap":[{"opp":"-1.0","odds":"6.600","header":"Home"},{"opp":"+1.0","odds":"1.110","header":"Away"},{"opp":"-0.5, -1.0","odds":"3.550","header":"Home"},{"opp":"+0.5, +1.0","odds":"1.275","header":"Away"},{"opp":"-0.5","odds":"2.675","header":"Home"},{"opp":"+0.5","odds":"1.450","header":"Away"},{"opp":"0.0","odds":"1.525","header":"Home"},{"opp":"0.0","odds":"2.425","header":"Away"},{"opp":"0.0, +0.5","odds":"1.325","header":"Home"},{"opp":"0.0, -0.5","odds":"3.300","header":"Away"},{"opp":"+0.5","odds":"1.220","header":"Home"},{"opp":"-0.5","odds":"4.150","header":"Away"},{"opp":"+0.5, +1.0","odds":"1.120","header":"Home"},{"opp":"-0.5, -1.0","odds":"6.250","header":"Away"}],"alternative_1st_half_goal_line":[{"goals":"0.5, 1.0","odds":"1.650","header":"Over"},{"goals":"0.5, 1.0","odds":"2.200","header":"Under"},{"goals":"1.0, 1.5","odds":"2.600","header":"Over"},{"goals":"1.0, 1.5","odds":"1.475","header":"Under"},{"goals":"1.5","odds":"3.100","header":"Over"},{"goals":"1.5","odds":"1.350","header":"Under"},{"goals":"1.5, 2.0","odds":"4.150","header":"Over"},{"goals":"1.5, 2.0","odds":"1.220","header":"Under"}]}},"goals":{"updated_at":"1532570396","sp":{"goals_over_under":[{"goals":"2.5","odds":"2.10","header":"Over"},{"goals":"2.5","odds":"1.70","header":"Under"}],"alternative_total_goals":[{"goals":"0.5","odds":"1.07","header":"Over "},{"goals":"0.5","odds":"9.00","header":"Under"},{"goals":"1.5","odds":"1.36","header":"Over "},{"goals":"1.5","odds":"3.00","header":"Under"},{"goals":"3.5","odds":"3.75","header":"Over "},{"goals":"3.5","odds":"1.25","header":"Under"},{"goals":"4.5","odds":"8.00","header":"Over "},{"goals":"4.5","odds":"1.08","header":"Under"},{"goals":"5.5","odds":"19.00","header":"Over "},{"goals":"5.5","odds":"1.02","header":"Under"}],"result_total_goals":[{"opp":"KPV & Over 2.5","odds":"3.40"},{"opp":"KPV & Under 2.5","odds":"4.00"},{"opp":"Draw & Over 2.5","odds":"15.00"},{"opp":"Draw & Under  2.5","odds":"4.00"},{"opp":"AC Oulu & Over 2.5","odds":"7.00"},{"opp":"AC Oulu & Under 2.5","odds":"7.00"}],"total_goals_both_teams_to_score":[{"opp":"Over 2.5 & Yes","odds":"2.50"},{"opp":"Over 2.5 & No","odds":"9.50"},{"opp":"Under 2.5 & Yes","odds":"6.50"},{"opp":"Under 2.5 & No","odds":"2.10"}],"exact_total_goals":[{"opp":"0 Goals","odds":"9.00"},{"opp":"1 Goal","odds":"4.33"},{"opp":"2 Goals","odds":"3.50"},{"opp":"3 Goals","odds":"4.33"},{"opp":"4 Goals","odds":"6.50"},{"opp":"5 Goals","odds":"13.00"},{"opp":"6 Goals","odds":"29.00"},{"opp":"7+ Goals","odds":"41.00"}],"number_of_goals_in_match":[{"opp":"Under 2 goals","odds":"3.00"},{"opp":"2 or 3 goals","odds":"1.95"},{"opp":"Over 3 goals","odds":"3.75"}],"both_teams_to_score":[{"opp":"Yes","odds":"1.91"},{"opp":"No","odds":"1.80"}],"teams_to_score":[{"opp":"Both Teams","odds":"1.91"},{"opp":"KPV Only","odds":"3.10"},{"opp":"No Goal","odds":"9.00"},{"opp":"AC Oulu Only","odds":"6.00"}],"both_teams_to_score_in_1st_half":[{"opp":"Yes","odds":"5.50"},{"opp":"No","odds":"1.14"}],"both_teams_to_score_in_2nd_half":[{"opp":"Yes","odds":"3.75"},{"opp":"No","odds":"1.25"}],"both_teams_to_score_1st_half_2nd_half":[{"opp":"Yes \/ Yes","odds":"19.00"},{"opp":"Yes \/ No","odds":"6.50"},{"opp":"No \/ Yes","odds":"4.00"},{"opp":"No \/ No","odds":"1.50"}],"first_half_goals":[{"goals":"0.5","odds":"1.44","header":"Over"},{"goals":"0.5","odds":"2.62","header":"Under"},{"goals":"1.5","odds":"3.25","header":"Over"},{"goals":"1.5","odds":"1.33","header":"Under"},{"goals":"2.5","odds":"9.00","header":"Over"},{"goals":"2.5","odds":"1.07","header":"Under"},{"goals":"3.5","odds":"26.00","header":"Over"},{"goals":"3.5","odds":"1.01","header":"Under"}],"exact_1st_half_goals":[{"opp":"0 Goals","odds":"2.62"},{"opp":"1 Goal","odds":"2.50"},{"opp":"2 Goals","odds":"4.50"},{"opp":"3 Goals","odds":"12.00"},{"opp":"4 Goals","odds":"34.00"},{"opp":"5+ Goals","odds":"81.00"}],"total_goal_minutes":[{"opp":"Over 130 minutes","odds":"2.10"},{"opp":"110 To 130 minutes inc.","odds":"8.50"},{"opp":"Under 110 minutes","odds":"1.91"}],"first_team_to_score":[{"opp":"KPV","odds":"1.62"},{"opp":"No Goals","odds":"9.00"},{"opp":"AC Oulu","odds":"2.60"}],"early_goal":[{"opp":"Goal before 31:00","odds":"1.83"},{"opp":"No Goal before 31:00","odds":"1.83"}],"late_goal":[{"opp":"Goal after 70:59","odds":"1.83"},{"opp":"No Goal after 70:59","odds":"1.83"}],"time_of_first_goal_brackets":[{"opp":"1-10","odds":"4.75"},{"opp":"11-20","odds":"5.50"},{"opp":"21-30","odds":"6.50"},{"opp":"31-40","odds":"7.00"},{"opp":"41-50","odds":"8.00"},{"opp":"51-60","odds":"12.00"},{"opp":"61-70","odds":"15.00"},{"opp":"71-80","odds":"19.00"},{"opp":"81 - Full Time","odds":"17.00"},{"opp":"No Goal","odds":"9.00"}],"2nd_half_goals":[{"goals":"0.5","odds":"1.29","header":"Over"},{"goals":"0.5","odds":"3.50","header":"Under"},{"goals":"1.5","odds":"2.25","header":"Over"},{"goals":"1.5","odds":"1.57","header":"Under"},{"goals":"2.5","odds":"5.50","header":"Over"},{"goals":"2.5","odds":"1.14","header":"Under"},{"goals":"3.5","odds":"15.00","header":"Over"},{"goals":"3.5","odds":"1.03","header":"Under"}],"exact_2nd_half_goals":[{"opp":"0 Goals","odds":"3.50"},{"opp":"1 Goal","odds":"2.62"},{"opp":"2 Goals","odds":"3.75"},{"opp":"3 Goals","odds":"7.50"},{"opp":"4 Goals","odds":"21.00"},{"opp":"5+ Goals","odds":"34.00"}],"half_with_most_goals":[{"opp":"1st Half","odds":"3.10"},{"opp":"2nd Half","odds":"2.10"},{"opp":"Tie","odds":"3.40"}],"home_team_highest_scoring_half":[{"opp":"KPV - 1st Half","odds":"3.40"},{"opp":"KPV - 2nd Half","odds":"2.40"},{"opp":"KPV - Tie","odds":"2.40"}],"away_team_highest_scoring_half":[{"opp":"AC Oulu - 1st Half","odds":"4.00"},{"opp":"AC Oulu - 2nd Half","odds":"2.88"},{"opp":"AC Oulu - Tie","odds":"1.95"}],"home_team_exact_goals":[{"opp":"KPV - 0 Goals","odds":"3.75"},{"opp":"KPV - 1 Goal","odds":"2.62"},{"opp":"KPV - 2 Goals","odds":"3.60"},{"opp":"KPV - 3+ Goals","odds":"4.50"}],"away_team_exact_goals":[{"opp":"AC Oulu - 0 Goals","odds":"2.50"},{"opp":"AC Oulu - 1 Goal","odds":"2.50"},{"opp":"AC Oulu - 2 Goals","odds":"4.75"},{"opp":"AC Oulu - 3+ Goals","odds":"11.00"}],"time_of_1st_team_goal":[{"opp":"KPV - Goal before 50:00","odds":"1.83"},{"opp":"KPV - No Goal before 50:00","odds":"1.83"},{"opp":"AC Oulu - Goal before 72:00","odds":"1.83"},{"opp":"AC Oulu - No Goal before 72:00","odds":"1.83"}],"goals_odd_even":[{"opp":"Even","odds":"1.90"},{"opp":"Odd","odds":"1.95"}],"home_team_odd_even_goals":[{"opp":"KPV - Even","odds":"1.80"},{"opp":"KPV - Odd","odds":"1.91"}],"away_team_odd_even_goals":[{"opp":"AC Oulu - Even","odds":"1.67"},{"opp":"AC Oulu - Odd","odds":"2.10"}],"1st_half_goals_odd_even":[{"opp":"Odd","odds":"2.10"},{"opp":"Even","odds":"1.73"}],"last_team_to_score":[{"opp":"KPV","odds":"1.62"},{"opp":"No Goal","odds":"9.00"},{"opp":"AC Oulu","odds":"2.60"}],"first_10_minutes_(00:00_09:59)":[{"name":"Goals","handicap":"0.5","odds":"4.50","header":"Over"},{"name":"Goals","handicap":"0.5","odds":"1.18","header":"Under"}]}},"half":{"updated_at":"1532570513","sp":{"half_time_result":[{"opp":"1","odds":"2.75"},{"opp":"X","odds":"2.10"},{"opp":"2","odds":"4.33"}],"half_time_double_chance":[{"opp":"1X","odds":"1.20"},{"opp":"X2","odds":"1.40"},{"opp":"12","odds":"1.67"}],"half_time_result_both_teams_to_score":[{"opp":"KPV & Yes","odds":"21.00"},{"opp":"KPV & No","odds":"2.88"},{"opp":"Draw & Yes","odds":"8.50"},{"opp":"Draw & No","odds":"2.60"},{"opp":"AC Oulu & Yes","odds":"29.00"},{"opp":"AC Oulu & No","odds":"4.75"}],"half_time_result_total_goals":[{"opp":"KPV & Over 1.5","odds":"7.00"},{"opp":"KPV & Under 1.5","odds":"3.75"},{"opp":"Draw & Over 1.5","odds":"8.50"},{"opp":"Draw & Under 1.5","odds":"2.62"},{"opp":"AC Oulu & Over 1.5","odds":"13.00"},{"opp":"AC Oulu & Under 1.5","odds":"5.50"}],"half_time_correct_score":[{"opp":"1-0","odds":"3.75","header":"Home"},{"opp":"0-0","odds":"2.62","header":"X"},{"opp":"1-0","odds":"5.50","header":"Away"},{"opp":"2-0","odds":"11.00","header":"Home"},{"opp":"1-1","odds":"8.50","header":"X"},{"opp":"2-0","odds":"21.00","header":"Away"},{"opp":"2-1","odds":"23.00","header":"Home"},{"opp":"2-2","odds":"67.00","header":"X"},{"opp":"2-1","odds":"34.00","header":"Away"},{"opp":"3-0","odds":"41.00","header":"Home"},{"opp":"3-0","odds":"81.00","header":"Away"},{"opp":"3-1","odds":"67.00","header":"Home"},{"opp":"3-1","odds":"126.00","header":"Away"},{"opp":"3-2","odds":"251.00","header":"Home"},{"opp":"3-2","odds":"351.00","header":"Away"},{"opp":"4-0","odds":"126.00","header":"Home"},{"opp":"4-1","odds":"301.00","header":"Home"}],"both_teams_to_score_in_1st_half":[{"opp":"Yes","odds":"5.50"},{"opp":"No","odds":"1.14"}],"both_teams_to_score_in_2nd_half":[{"opp":"Yes","odds":"3.75"},{"opp":"No","odds":"1.25"}],"both_teams_to_score_1st_half_2nd_half":[{"opp":"Yes \/ Yes","odds":"19.00"},{"opp":"Yes \/ No","odds":"6.50"},{"opp":"No \/ Yes","odds":"4.00"},{"opp":"No \/ No","odds":"1.50"}],"1st_half_asian_handicap":[{"opp":"0.0, -0.5","odds":"2.100","header":"Home"},{"opp":"0.0, +0.5","odds":"1.700","header":"Away"}],"1st_half_goal_line":[{"goals":"1.0","odds":"2.075","header":"Over"},{"goals":"1.0","odds":"1.725","header":"Under"}],"alternative_1st_half_asian_handicap":[{"opp":"-1.0","odds":"6.600","header":"Home"},{"opp":"+1.0","odds":"1.110","header":"Away"},{"opp":"-0.5, -1.0","odds":"3.550","header":"Home"},{"opp":"+0.5, +1.0","odds":"1.275","header":"Away"},{"opp":"-0.5","odds":"2.675","header":"Home"},{"opp":"+0.5","odds":"1.450","header":"Away"},{"opp":"0.0","odds":"1.525","header":"Home"},{"opp":"0.0","odds":"2.425","header":"Away"},{"opp":"0.0, +0.5","odds":"1.325","header":"Home"},{"opp":"0.0, -0.5","odds":"3.300","header":"Away"},{"opp":"+0.5","odds":"1.220","header":"Home"},{"opp":"-0.5","odds":"4.150","header":"Away"},{"opp":"+0.5, +1.0","odds":"1.120","header":"Home"},{"opp":"-0.5, -1.0","odds":"6.250","header":"Away"}],"alternative_1st_half_goal_line":[{"goals":"0.5, 1.0","odds":"1.650","header":"Over"},{"goals":"0.5, 1.0","odds":"2.200","header":"Under"},{"goals":"1.0, 1.5","odds":"2.600","header":"Over"},{"goals":"1.0, 1.5","odds":"1.475","header":"Under"},{"goals":"1.5","odds":"3.100","header":"Over"},{"goals":"1.5","odds":"1.350","header":"Under"},{"goals":"1.5, 2.0","odds":"4.150","header":"Over"},{"goals":"1.5, 2.0","odds":"1.220","header":"Under"}],"1st_half_handicap":[{"opp":"KPV  -1.0","odds":"8.50"},{"opp":"Tie - AC Oulu +1.0","odds":"3.40"},{"opp":"AC Oulu  +1.0","odds":"1.44"}],"alternative_1st_half_handicap_result":[{"opp":"-2.0","odds":"21.00","header":"Home"},{"opp":"+2.0","odds":"10.00","header":"Tie"},{"opp":"+2.0","odds":"1.06","header":"Away"},{"opp":"+1.0","odds":"1.20","header":"Home"},{"opp":"-1.0","odds":"4.75","header":"Tie"},{"opp":"-1.0","odds":"17.00","header":"Away"}],"first_half_goals":[{"goals":"0.5","odds":"1.44","header":"Over"},{"goals":"0.5","odds":"2.62","header":"Under"},{"goals":"1.5","odds":"3.25","header":"Over"},{"goals":"1.5","odds":"1.33","header":"Under"},{"goals":"2.5","odds":"9.00","header":"Over"},{"goals":"2.5","odds":"1.07","header":"Under"},{"goals":"3.5","odds":"26.00","header":"Over"},{"goals":"3.5","odds":"1.01","header":"Under"}],"exact_1st_half_goals":[{"opp":"0 Goals","odds":"2.62"},{"opp":"1 Goal","odds":"2.50"},{"opp":"2 Goals","odds":"4.50"},{"opp":"3 Goals","odds":"12.00"},{"opp":"4 Goals","odds":"34.00"},{"opp":"5+ Goals","odds":"81.00"}],"1st_half_goals_odd_even":[{"opp":"Odd","odds":"2.10"},{"opp":"Even","odds":"1.73"}],"to_score_in_half":[{"name":"1st Half","odds":"2.00","header":"Yes"},{"name":"1st Half","odds":"1.73","header":"No"},{"name":"2nd Half","odds":"1.67","header":"Yes"},{"name":"2nd Half","odds":"2.10","header":"No"},{"name":"1st Half","odds":"2.62","header":"Yes"},{"name":"1st Half","odds":"1.44","header":"No"},{"name":"2nd Half","odds":"2.20","header":"Yes"},{"name":"2nd Half","odds":"1.62","header":"No"}],"half_with_most_goals":[{"opp":"1st Half","odds":"3.10"},{"opp":"2nd Half","odds":"2.10"},{"opp":"Tie","odds":"3.40"}],"home_team_highest_scoring_half":[{"opp":"KPV - 1st Half","odds":"3.40"},{"opp":"KPV - 2nd Half","odds":"2.40"},{"opp":"KPV - Tie","odds":"2.40"}],"away_team_highest_scoring_half":[{"opp":"AC Oulu - 1st Half","odds":"4.00"},{"opp":"AC Oulu - 2nd Half","odds":"2.88"},{"opp":"AC Oulu - Tie","odds":"1.95"}],"2nd_half_result":[{"opp":"1","odds":"2.30"},{"opp":"X","odds":"2.38"},{"opp":"2","odds":"3.75"}],"2nd_half_goals":[{"goals":"0.5","odds":"1.29","header":"Over"},{"goals":"0.5","odds":"3.50","header":"Under"},{"goals":"1.5","odds":"2.25","header":"Over"},{"goals":"1.5","odds":"1.57","header":"Under"},{"goals":"2.5","odds":"5.50","header":"Over"},{"goals":"2.5","odds":"1.14","header":"Under"},{"goals":"3.5","odds":"15.00","header":"Over"},{"goals":"3.5","odds":"1.03","header":"Under"}],"exact_2nd_half_goals":[{"opp":"0 Goals","odds":"3.50"},{"opp":"1 Goal","odds":"2.62"},{"opp":"2 Goals","odds":"3.75"},{"opp":"3 Goals","odds":"7.50"},{"opp":"4 Goals","odds":"21.00"},{"opp":"5+ Goals","odds":"34.00"}],"2nd_half_goals_odd_even":[{"opp":"Even","odds":"1.73"},{"opp":"Odd","odds":"2.00"}]}},"main":{"updated_at":"1532570359","sp":{"full_time_result":[{"opp":"1","odds":"1.95"},{"opp":"X","odds":"3.40"},{"opp":"2","odds":"3.50"}],"double_chance":[{"opp":"1X","odds":"1.29"},{"opp":"X2","odds":"1.80"},{"opp":"12","odds":"1.30"}],"correct_score":[{"opp":"1-0","odds":"6.50","header":"Home"},{"opp":"0-0","odds":"9.00","header":"X"},{"opp":"1-0","odds":"9.50","header":"Away"},{"opp":"2-0","odds":"8.50","header":"Home"},{"opp":"1-1","odds":"6.50","header":"X"},{"opp":"2-0","odds":"17.00","header":"Away"},{"opp":"2-1","odds":"9.00","header":"Home"},{"opp":"2-2","odds":"17.00","header":"X"},{"opp":"2-1","odds":"13.00","header":"Away"},{"opp":"3-0","odds":"17.00","header":"Home"},{"opp":"3-3","odds":"67.00","header":"X"},{"opp":"3-0","odds":"41.00","header":"Away"},{"opp":"3-1","odds":"17.00","header":"Home"},{"opp":"3-1","odds":"34.00","header":"Away"},{"opp":"3-2","odds":"29.00","header":"Home"},{"opp":"3-2","odds":"41.00","header":"Away"},{"opp":"4-0","odds":"41.00","header":"Home"},{"opp":"4-0","odds":"101.00","header":"Away"},{"opp":"4-1","odds":"41.00","header":"Home"},{"opp":"4-1","odds":"81.00","header":"Away"},{"opp":"4-2","odds":"51.00","header":"Home"},{"opp":"4-2","odds":"101.00","header":"Away"},{"opp":"4-3","odds":"126.00","header":"Home"},{"opp":"4-3","odds":"151.00","header":"Away"},{"opp":"5-0","odds":"81.00","header":"Home"},{"opp":"5-1","odds":"301.00","header":"Away"},{"opp":"5-1","odds":"81.00","header":"Home"},{"opp":"5-2","odds":"151.00","header":"Home"},{"opp":"6-0","odds":"251.00","header":"Home"},{"opp":"6-1","odds":"251.00","header":"Home"}],"half_time_full_time":[{"opp":"KPV - KPV","odds":"3.20"},{"opp":"KPV - Draw","odds":"15.00"},{"opp":"KPV - AC Oulu","odds":"41.00"},{"opp":"Draw - KPV","odds":"4.75"},{"opp":"Draw - Draw","odds":"5.00"},{"opp":"Draw - AC Oulu","odds":"8.00"},{"opp":"AC Oulu - KPV","odds":"26.00"},{"opp":"AC Oulu - Draw","odds":"15.00"},{"opp":"AC Oulu - AC Oulu","odds":"6.50"}],"goals_over_under":[{"goals":"2.5","odds":"2.10","header":"Over"},{"goals":"2.5","odds":"1.70","header":"Under"}],"both_teams_to_score":[{"opp":"Yes","odds":"1.91"},{"opp":"No","odds":"1.80"}],"asian_handicap":[{"opp":"-0.5","odds":"2.025","header":"Home"},{"opp":"+0.5","odds":"1.825","header":"Away"}],"goal_line":[{"goals":"2.0, 2.5","odds":"1.900","header":"Over"},{"goals":"2.0, 2.5","odds":"1.950","header":"Under"}],"alternative_asian_handicap":[{"opp":"-1.5, -2.0","odds":"4.800","header":"Home"},{"opp":"+1.5, +2.0","odds":"1.175","header":"Away"},{"opp":"-1.5","odds":"3.700","header":"Home"},{"opp":"+1.5","odds":"1.260","header":"Away"},{"opp":"-1.0, -1.5","odds":"3.450","header":"Home"},{"opp":"+1.0, +1.5","odds":"1.300","header":"Away"},{"opp":"-1.0","odds":"3.000","header":"Home"},{"opp":"+1.0","odds":"1.375","header":"Away"},{"opp":"-0.5, -1.0","odds":"2.300","header":"Home"},{"opp":"+0.5, +1.0","odds":"1.600","header":"Away"},{"opp":"0.0, -0.5","odds":"1.725","header":"Home"},{"opp":"0.0, +0.5","odds":"2.075","header":"Away"},{"opp":"0.0","odds":"1.475","header":"Home"},{"opp":"0.0","odds":"2.600","header":"Away"},{"opp":"0.0, +0.5","odds":"1.375","header":"Home"},{"opp":"0.0, -0.5","odds":"3.000","header":"Away"},{"opp":"+0.5","odds":"1.300","header":"Home"},{"opp":"-0.5","odds":"3.450","header":"Away"},{"opp":"+0.5, +1.0","odds":"1.190","header":"Home"},{"opp":"-0.5, -1.0","odds":"4.500","header":"Away"}],"alternative_goal_line":[{"goals":"1.0","odds":"1.100","header":"Over"},{"goals":"1.0","odds":"7.000","header":"Under"},{"goals":"1.0, 1.5","odds":"1.230","header":"Over"},{"goals":"1.0, 1.5","odds":"4.000","header":"Under"},{"goals":"1.5","odds":"1.375","header":"Over"},{"goals":"1.5","odds":"3.000","header":"Under"},{"goals":"1.5, 2.0","odds":"1.450","header":"Over"},{"goals":"1.5, 2.0","odds":"2.675","header":"Under"},{"goals":"2.0","odds":"1.600","header":"Over"},{"goals":"2.0","odds":"2.300","header":"Under"},{"goals":"2.5","odds":"2.100","header":"Over"},{"goals":"2.5","odds":"1.700","header":"Under"},{"goals":"2.5, 3.0","odds":"2.425","header":"Over"},{"goals":"2.5, 3.0","odds":"1.525","header":"Under"},{"goals":"3.0","odds":"3.100","header":"Over"},{"goals":"3.0","odds":"1.350","header":"Under"},{"goals":"3.0, 3.5","odds":"3.450","header":"Over"},{"goals":"3.0, 3.5","odds":"1.300","header":"Under"},{"goals":"3.5","odds":"3.800","header":"Over"},{"goals":"3.5","odds":"1.250","header":"Under"},{"goals":"3.5, 4.0","odds":"4.800","header":"Over"},{"goals":"3.5, 4.0","odds":"1.175","header":"Under"},{"goals":"4.0","odds":"7.000","header":"Over"},{"goals":"4.0","odds":"1.100","header":"Under"}],"draw_no_bet":[{"opp":"KPV","odds":"1.44"},{"opp":"AC Oulu","odds":"2.62"}],"result_both_teams_to_score":[{"name":"KPV","odds":"4.50","header":"Yes"},{"name":"KPV","odds":"3.10","header":"No"},{"name":"AC Oulu","odds":"8.00","header":"Yes"},{"name":"AC Oulu","odds":"6.00","header":"No"},{"name":"Draw","odds":"5.00","header":"Yes"},{"name":"Draw","odds":"9.00","header":"No"}],"handicap_result":[{"opp":"KPV (-1)","odds":"3.60"},{"opp":"Tie - (AC Oulu +1)","odds":"3.60"},{"opp":"AC Oulu (+1)","odds":"1.80"}],"alternative_handicap_result":[{"opp":"-3.0","odds":"15.00","header":"Home"},{"opp":"+3.0","odds":"10.00","header":"Tie"},{"opp":"+3.0","odds":"1.06","header":"Away"},{"opp":"-2.0","odds":"8.00","header":"Home"},{"opp":"+2.0","odds":"5.50","header":"Tie"},{"opp":"+2.0","odds":"1.25","header":"Away"},{"opp":"+1.0","odds":"1.29","header":"Home"},{"opp":"-1.0","odds":"5.00","header":"Tie"},{"opp":"-1.0","odds":"8.00","header":"Away"},{"opp":"+2.0","odds":"1.06","header":"Home"},{"opp":"-2.0","odds":"10.00","header":"Tie"},{"opp":"-2.0","odds":"17.00","header":"Away"}],"winning_margin":[{"goals":" 1","odds":"3.60","header":"Home"},{"goals":" 1","odds":"5.00","header":"Away"},{"goals":" 2","odds":"5.50","header":"Home"},{"goals":" 2","odds":"10.00","header":"Away"},{"goals":" 3","odds":"10.00","header":"Home"},{"goals":" 3","odds":"34.00","header":"Away"},{"goals":" 4+","odds":"15.00","header":"Home"},{"goals":" 4+","odds":"81.00","header":"Away"},{"goals":"Score Draw","odds":"5.00","header":"Home"},{"goals":"No Goal","odds":"9.00","header":"Home"}]}},"schedule":{"updated_at":"1532570319","sp":{"main":[{"odds":"1.900"},{"odds":"1.950"}]}},"specials":{"updated_at":"1532570555","sp":{"specials":[{"name":"To Win From Behind","odds":"9.00","header":"Home"},{"name":"To Win From Behind","odds":"13.00","header":"Away"},{"name":"To Win to Nil","odds":"3.10","header":"Home"},{"name":"To Win to Nil","odds":"6.00","header":"Away"},{"name":"To Win Either Half","odds":"1.53","header":"Home"},{"name":"To Win Either Half","odds":"2.25","header":"Away"},{"name":"To Win Both Halves","odds":"6.50","header":"Home"},{"name":"To Win Both Halves","odds":"17.00","header":"Away"},{"name":"To Score in Both Halves","odds":"3.40","header":"Home"},{"name":"To Score in Both Halves","odds":"6.00","header":"Away"}],"to_score_in_half":[{"name":"1st Half","odds":"2.00","header":"Yes"},{"name":"1st Half","odds":"1.73","header":"No"},{"name":"2nd Half","odds":"1.67","header":"Yes"},{"name":"2nd Half","odds":"2.10","header":"No"},{"name":"1st Half","odds":"2.62","header":"Yes"},{"name":"1st Half","odds":"1.44","header":"No"},{"name":"2nd Half","odds":"2.20","header":"Yes"},{"name":"2nd Half","odds":"1.62","header":"No"}]}}}]}}