{"odd":{"success":1,"results":[{"FI":"75403789","event_id":"847739","asian_lines":{"updated_at":"1532570917","sp":[]},"goals":{"updated_at":"1532570553","sp":{"goals_over_under":[{"goals":"2.5","odds":"1.50","header":"Over"},{"goals":"2.5","odds":"2.50","header":"Under"}],"first_team_to_score":[{"opp":"UD Tamaraceite","odds":"2.30"},{"opp":"No Goals","odds":"19.00"},{"opp":"Las Palmas B","odds":"1.62"}],"home_team_highest_scoring_half":[{"opp":"UD Tamaraceite - 1st Half","odds":"3.60"},{"opp":"UD Tamaraceite - 2nd Half","odds":"2.60"},{"opp":"UD Tamaraceite - Tie","odds":"2.20"}],"away_team_highest_scoring_half":[{"opp":"Las Palmas B - 1st Half","odds":"3.20"},{"opp":"Las Palmas B - 2nd Half","odds":"2.20"},{"opp":"Las Palmas B - Tie","odds":"3.00"}],"goals_odd_even":[{"opp":"Even","odds":"1.90"},{"opp":"Odd","odds":"1.95"}],"home_team_odd_even_goals":[{"opp":"UD Tamaraceite - Even","odds":"1.73"},{"opp":"UD Tamaraceite - Odd","odds":"2.00"}],"away_team_odd_even_goals":[{"opp":"Las Palmas B - Even","odds":"1.83"},{"opp":"Las Palmas B - Odd","odds":"1.83"}],"1st_half_goals_odd_even":[{"opp":"Odd","odds":"2.00"},{"opp":"Even","odds":"1.80"}]}},"half":{"updated_at":"1532570563","sp":{"half_time_result":[{"opp":"1","odds":"4.00"},{"opp":"X","odds":"2.40"},{"opp":"2","odds":"2.20"}],"half_time_double_chance":[{"opp":"1X","odds":"1.62"},{"opp":"X2","odds":"1.22"},{"opp":"12","odds":"1.53"}],"half_time_correct_score":[{"opp":"1-0","odds":"6.50","header":"Home"},{"opp":"0-0","odds":"3.75","header":"X"},{"opp":"1-0","odds":"4.00","header":"Away"},{"opp":"2-0","odds":"21.00","header":"Home"},{"opp":"1-1","odds":"7.50","header":"X"},{"opp":"2-0","odds":"8.50","header":"Away"},{"opp":"2-1","odds":"23.00","header":"Home"},{"opp":"2-2","odds":"41.00","header":"X"},{"opp":"2-1","odds":"17.00","header":"Away"},{"opp":"3-0","odds":"67.00","header":"Home"},{"opp":"3-0","odds":"23.00","header":"Away"},{"opp":"3-1","odds":"67.00","header":"Home"},{"opp":"3-1","odds":"41.00","header":"Away"},{"opp":"3-2","odds":"151.00","header":"Home"},{"opp":"3-2","odds":"101.00","header":"Away"},{"opp":"4-0","odds":"67.00","header":"Away"},{"opp":"4-1","odds":"101.00","header":"Away"}],"1st_half_goals_odd_even":[{"opp":"Odd","odds":"2.00"},{"opp":"Even","odds":"1.80"}],"home_team_highest_scoring_half":[{"opp":"UD Tamaraceite - 1st Half","odds":"3.60"},{"opp":"UD Tamaraceite - 2nd Half","odds":"2.60"},{"opp":"UD Tamaraceite - Tie","odds":"2.20"}],"away_team_highest_scoring_half":[{"opp":"Las Palmas B - 1st Half","odds":"3.20"},{"opp":"Las Palmas B - 2nd Half","odds":"2.20"},{"opp":"Las Palmas B - Tie","odds":"3.00"}],"2nd_half_goals_odd_even":[{"opp":"Even","odds":"1.80"},{"opp":"Odd","odds":"1.91"}]}},"main":{"updated_at":"1532570533","sp":{"full_time_result":[{"opp":"1","odds":"3.75"},{"opp":"X","odds":"4.00"},{"opp":"2","odds":"1.67"}],"double_chance":[{"opp":"1X","odds":"2.10"},{"opp":"X2","odds":"1.25"},{"opp":"12","odds":"1.22"}],"correct_score":[{"opp":"1-0","odds":"17.00","header":"Home"},{"opp":"0-0","odds":"19.00","header":"X"},{"opp":"1-0","odds":"10.00","header":"Away"},{"opp":"2-0","odds":"23.00","header":"Home"},{"opp":"1-1","odds":"8.50","header":"X"},{"opp":"2-0","odds":"10.00","header":"Away"},{"opp":"2-1","odds":"13.00","header":"Home"},{"opp":"2-2","odds":"13.00","header":"X"},{"opp":"2-1","odds":"8.50","header":"Away"},{"opp":"3-0","odds":"41.00","header":"Home"},{"opp":"3-3","odds":"41.00","header":"X"},{"opp":"3-0","odds":"15.00","header":"Away"},{"opp":"3-1","odds":"29.00","header":"Home"},{"opp":"4-4","odds":"126.00","header":"X"},{"opp":"3-1","odds":"12.00","header":"Away"},{"opp":"3-2","odds":"29.00","header":"Home"},{"opp":"3-2","odds":"19.00","header":"Away"},{"opp":"4-0","odds":"81.00","header":"Home"},{"opp":"4-0","odds":"26.00","header":"Away"},{"opp":"4-1","odds":"51.00","header":"Home"},{"opp":"4-1","odds":"21.00","header":"Away"},{"opp":"4-2","odds":"51.00","header":"Home"},{"opp":"4-2","odds":"34.00","header":"Away"},{"opp":"4-3","odds":"81.00","header":"Home"},{"opp":"4-3","odds":"51.00","header":"Away"},{"opp":"5-1","odds":"151.00","header":"Home"},{"opp":"5-0","odds":"41.00","header":"Away"},{"opp":"5-2","odds":"151.00","header":"Home"},{"opp":"5-1","odds":"41.00","header":"Away"},{"opp":"5-2","odds":"51.00","header":"Away"},{"opp":"5-3","odds":"101.00","header":"Away"},{"opp":"6-0","odds":"81.00","header":"Away"},{"opp":"6-1","odds":"81.00","header":"Away"},{"opp":"6-2","odds":"126.00","header":"Away"}],"half_time_full_time":[{"opp":"UD Tamaraceite - UD Tamaraceite","odds":"6.50"},{"opp":"UD Tamaraceite - Draw","odds":"15.00"},{"opp":"UD Tamaraceite - Las Palmas B","odds":"19.00"},{"opp":"Draw - UD Tamaraceite","odds":"9.50"},{"opp":"Draw - Draw","odds":"7.00"},{"opp":"Draw - Las Palmas B","odds":"5.00"},{"opp":"Las Palmas B - UD Tamaraceite","odds":"29.00"},{"opp":"Las Palmas B - Draw","odds":"15.00"},{"opp":"Las Palmas B - Las Palmas B","odds":"2.62"}],"goals_over_under":[{"goals":"2.5","odds":"1.50","header":"Over"},{"goals":"2.5","odds":"2.50","header":"Under"}],"draw_no_bet":[{"opp":"UD Tamaraceite","odds":"3.25"},{"opp":"Las Palmas B","odds":"1.33"}]}},"schedule":{"updated_at":"1532570845","sp":{"main":[{"odds":"3.75"},{"odds":"4.00"},{"odds":"1.67"}]}}}]}}